cleanpad/__init__.py
cleanpad/core.py
cleanpad-0.1.2.dist-info/licenses/LICENSE
tests/__init__.py
tests/test_core.py
cleanpad-0.1.2.dist-info/METADATA
cleanpad-0.1.2.dist-info/WHEEL
cleanpad-0.1.2.dist-info/top_level.txt
cleanpad-0.1.2.dist-info/RECORD
